PyFiFinder/__init__.py
PyFiFinder/pyf.py
PyFiFinder-0.0.22.2.dist-info/LICENSE.txt
PyFiFinder-0.0.22.2.dist-info/METADATA
PyFiFinder-0.0.22.2.dist-info/WHEEL
PyFiFinder-0.0.22.2.dist-info/top_level.txt
PyFiFinder-0.0.22.2.dist-info/RECORD
