Metadata-Version: 2.1
Name: PyFiFinder
Version: 0.0.22.2
Summary: this is a tool to search for archives by passing their specifc formats
Home-page: https://github.com/m4rkito/PyFiFinder
Author: M4rk(Marcelo almeida)
Author-email: marcelorap345@gmail.com
License: UNKNOWN
Platform: UNKNOWN
Classifier: Programming Language :: Python :: 3
Classifier: License :: OSI Approved :: MIT License
Classifier: Operating System :: OS Independent
Requires-Python: >=3.6
